yahoo_fin/__init__.py
yahoo_fin/news.py
yahoo_fin/options.py
yahoo_fin/options_test.py
yahoo_fin/stock_info.py
yahoo_fin/stock_info_test.py
yahoo_fin_cheese-0.8.9.6.dist-info/LICENSE.txt
yahoo_fin_cheese-0.8.9.6.dist-info/METADATA
yahoo_fin_cheese-0.8.9.6.dist-info/WHEEL
yahoo_fin_cheese-0.8.9.6.dist-info/top_level.txt
yahoo_fin_cheese-0.8.9.6.dist-info/RECORD
